xia_analytics/__init__.py
xia_analytics/analyzer.cpython-311-darwin.so
xia_analytics-0.0.8.dist-info/LICENSE.txt
xia_analytics-0.0.8.dist-info/METADATA
xia_analytics-0.0.8.dist-info/WHEEL
xia_analytics-0.0.8.dist-info/top_level.txt
xia_analytics-0.0.8.dist-info/RECORD
