Metadata-Version: 2.1
Name: xia-analytics
Version: 0.0.8
Summary: UNKNOWN
Home-page: https://develop.x-i-a.com/docs/xia-analytics/0.0.8/index.html
Author: X-I-A
Author-email: admin@x-i-a.com
License: UNKNOWN
Platform: UNKNOWN
Requires-Python: >=3.9
License-File: LICENSE.txt
Requires-Dist: xia-engine
